PyRwu/PyRwu.py
PyRwu/PyRwuDirty.py
PyRwu/PyRwuIniquity.py
PyRwu/__init__.py
PyRwu/conf.py
PyRwu/flags.py
PyRwu/frq_io.py
PyRwu/interpolate.py
PyRwu/pitch.py
PyRwu/resamp.py
PyRwu/settings.py
PyRwu/stretch.py
PyRwu/wave_io.py
PyRwu/effects/__init__.py
PyRwu/effects/base.py
PyRwu/effects/eb_flag.py
PyRwu/effects/g_flag.py
PyRwu/effects/gw_flag.py
PyRwu/effects/large_a_flag.py
PyRwu/effects/large_b_flag.py
PyRwu/effects/large_p_flag.py
PyRwu/effects/t_flag.py
PyRwu/effects/vf_flag.py
PyRwu-0.0.3.dist-info/LICENSE
PyRwu-0.0.3.dist-info/METADATA
PyRwu-0.0.3.dist-info/WHEEL
PyRwu-0.0.3.dist-info/top_level.txt
PyRwu-0.0.3.dist-info/RECORD
