Metadata-Version: 2.1
Name: PyRwu
Version: 0.0.3
Summary: UTAU's resampler emulater powerd by world
Home-page: https://github.com/delta-kimigatame/PyRwu
Author: delta_kimigatame
Author-email: sankaku.kuro@gmail.com
Project-URL: Bug Tracker, https://github.com/delta-kimigatame/PyRwu/issues
Classifier: Programming Language :: Python :: 3
Classifier: License :: OSI Approved :: MIT License
Classifier: Operating System :: OS Independent
Requires-Python: >=3.7
License-File: LICENSE
Requires-Dist: numpy
Requires-Dist: pyworld
